Metadata-Version: 1.0
Name: vie-distributions
Version: 0.1
Summary: Gaussian distributions
Home-page: UNKNOWN
Author: Aidoo Enoch Kwadwo
Author-email: aidooenochkwadwo@gmail.com
License: UNKNOWN
Platform: UNKNOWN
